[
  {
    "id": 1,
    "name": "David Wilson",
    "position": "CEO & Founder",
    "image": "https://placehold.co/400x500/0a1628/ffffff?text=David+Wilson",
    "bio": "Visionary leader with 20+ years of industry experience.",
    "social": {
      "facebook": "#",
      "twitter": "#",
      "linkedin": "#"
    }
  },
  {
    "id": 2,
    "name": "Emily Chen",
    "position": "Creative Director",
    "image": "https://placehold.co/400x500/1a1a1a/ffffff?text=Emily+Chen",
    "bio": "Award-winning creative professional.",
    "social": {
      "facebook": "#",
      "twitter": "#",
      "linkedin": "#"
    }
  },
  {
    "id": 3,
    "name": "James Miller",
    "position": "Technical Lead",
    "image": "https://placehold.co/400x500/2d2d2d/ffffff?text=James+Miller",
    "bio": "Expert in cutting-edge technologies.",
    "social": {
      "facebook": "#",
      "twitter": "#",
      "linkedin": "#"
    }
  },
  {
    "id": 4,
    "name": "Lisa Anderson",
    "position": "Marketing Manager",
    "image": "https://placehold.co/400x500/3d3d3d/ffffff?text=Lisa+Anderson",
    "bio": "Strategic marketing expert.",
    "social": {
      "facebook": "#",
      "twitter": "#",
      "linkedin": "#"
    }
  }
]
